MANIFEST.in
README.md
setup.py
scripts/shareboard
src/shareboard/__init__.py
src/shareboard/parser.py
src/shareboard/server.py
src/shareboard.egg-info/PKG-INFO
src/shareboard.egg-info/SOURCES.txt
src/shareboard.egg-info/dependency_links.txt
src/shareboard.egg-info/top_level.txt
src/shareboard.egg-info/zip-safe
src/shareboard/gui/__init__.py
src/shareboard/gui/main.py
src/shareboard/gui/server.py
src/shareboard/gui/viewer.py