Metadata-Version: 1.1
Name: shareboard
Version: 0.1.7
Summary: A local HTTP server based clipboard like pipe
Home-page: https://github.com/lambdalisue/Shareboard
Author: Alisue
Author-email: lambdalisue@hashnote.net
License: MIT
Download-URL: https://github.com/lambdalisue/Shareboard/tarball/master
Keywords: http clipboard pipe cui viewer
Platform: UNKNOWN
Classifier: Intended Audience :: Developers
Classifier: License :: OSI Approved :: MIT License
Classifier: Programming Language :: Python
Classifier: Topic :: Internet :: WWW/HTTP
